{
  "$schema": "https://flagd.dev/schema/v0/flags.json",
  "flags": {
    "productCatalogFailure": {
      "description": "Fail product catalog service on a specific product",
      "state": "ENABLED",
      "variants": {
        "on": true,
        "off": false
      },
      "defaultVariant": "off"
    },
    "recommendationServiceCacheFailure": {
      "description": "Fail recommendation service cache",
      "state": "ENABLED",
      "variants": {
        "on": true,
        "off": false
      },
      "defaultVariant": "off"
    },
    "kafkaQueueProblems": {
      "description": "Overloads Kafka queue while simultaneously introducing a consumer side delay leading to a lag spike",
      "state": "ENABLED",
      "variants": {
        "on": 100,
        "off": 0
      },
      "defaultVariant": "off"
    },
    "loadgeneratorFloodHomepage": {
      "description": "Flood the frontend with a large amount of requests.",
      "state": "ENABLED",
      "variants": {
        "on": 100,
        "off": 0
      },
      "defaultVariant": "off"
    },
    "imageSlowLoad": {
      "description": "slow loading images in the frontend",
      "state": "ENABLED",
      "variants": {
        "10sec": 10000,
        "5sec": 5000,
        "off": 0
      },
      "defaultVariant": "off"
    }
  }
}
